photoage/__init__.py
photoage/photoage.py
photoage-0.1.1.data/scripts/photoage
photoage-0.1.1.dist-info/LICENSE
photoage-0.1.1.dist-info/METADATA
photoage-0.1.1.dist-info/WHEEL
photoage-0.1.1.dist-info/top_level.txt
photoage-0.1.1.dist-info/RECORD
