Metadata-Version: 2.1
Name: photoage
Version: 0.1.1
Summary: Calculate the age of a photo.
Home-page: https://github.com/johnlinp/photoage
Author: johnlinp
Author-email: johnlinp@gmail.com
License: New BSD License
Platform: UNKNOWN
Requires-Dist: exifread
